setup.py
Flask_Intercom.egg-info/PKG-INFO
Flask_Intercom.egg-info/SOURCES.txt
Flask_Intercom.egg-info/dependency_links.txt
Flask_Intercom.egg-info/requires.txt
Flask_Intercom.egg-info/top_level.txt
flask_intercom/__init__.py
flask_intercom/extension.py
flask_intercom/signals.py
flask_intercom.egg-info/PKG-INFO
flask_intercom.egg-info/SOURCES.txt
flask_intercom.egg-info/dependency_links.txt
flask_intercom.egg-info/requires.txt
flask_intercom.egg-info/top_level.txt