Metadata-Version: 1.0
Name: Flask-Intercom
Version: 0.1.0
Summary: Flask-Intercom
Home-page: https://github.com/raicheff/flask-intercom
Author: Boris Raicheff
Author-email: b@raicheff.com
License: UNKNOWN
Platform: UNKNOWN
